{
  "products": [
    {
      "name": "FORMAL SHIRT",
      "tag": "19",
      "price": 280,
      "id": 4
    },
    {
      "name": "WHITE SHIRT",
      "tag": "7",
      "price": 280,
      "id": 5
    },
    {
      "name": "BLUE SHIRT",
      "tag": "20",
      "price": 380,
      "id": 6
    },
    {
      "name": "CASUAL SHOES",
      "tag": "21",
      "price": 180,
      "id": 7
    },
    {
      "name": "FORMAL SHOES",
      "tag": "22",
      "price": 200,
      "id": 8
    },
    {
      "name": "TREKK SHOES",
      "tag": "23",
      "price": 250,
      "id": 9
    },
    {
      "name": "BLAZER",
      "tag": "24",
      "price": 500,
      "id": 10
    },
    {
      "name": "BLAZER",
      "tag": "26",
      "price": 450,
      "id": 11
    },
    {
      "name": "CLOCK",
      "tag": "34",
      "price": 150,
      "id": 12
    }
  ],
  "product2": [
    {
      "name": "CENTER TABLE",
      "tag": "30",
      "price": 280,
      "id": 1
    },
    {
      "name": "MEDIA TABLE",
      "tag": "32",
      "price": 280,
      "id": 2
    },
    {
      "name": "ENTERTAINMENT TABLE",
      "tag": "31",
      "price": 380,
      "id": 3
    },
    {
      "name": "2 SEATER SOFA",
      "tag": "33",
      "price": 180,
      "id": 4
    },
    {
      "name": "STREET LAMP",
      "tag": "6",
      "price": 200,
      "id": 5
    },
    {
      " name": "STREET LAMP",
      "tag": "9",
      " price": 250,
      "id": 6
    },
    {
      "name": "ANKLET",
      "tag": "10",
      "price": 500,
      "id": 7
    },
    {
      "name": "STONE BANGLE",
      "tag": "11",
      "price": 450,
      "id": 8
    },
    {
      "name": "CLOCK",
      "tag": "34",
      "price": 150,
      "id": 9
    }
  ]
}
